pidb/__init__.py
pidb/__main__.py
pidb/conftest.py
pidb/control.py
pidb/exceptions.py
pidb/fields.py
pidb/models.py
pidb/views.py
pidb/api/__init__.py
pidb/api/health.py
pidb/api/v1.py
pidb/auth/__init__.py
pidb/auth/forms.py
pidb/auth/models.py
pidb/callbacks/__init__.py
pidb/static/android-chrome-192x192.png
pidb/static/android-chrome-512x512.png
pidb/static/apple-touch-icon.png
pidb/static/browserconfig.xml
pidb/static/code.css
pidb/static/favicon-16x16.ico
pidb/static/favicon-16x16.png
pidb/static/favicon-32x32.ico
pidb/static/favicon-32x32.png
pidb/static/favicon.ico
pidb/static/mstile-144x144.png
pidb/static/mstile-150x150.png
pidb/static/mstile-310x150.png
pidb/static/mstile-310x310.png
pidb/static/mstile-70x70.png
pidb/static/safari-pinned-tab.svg
pidb/static/site.webmanifest
pidb/static/style.css
pidb/static/img/benjamin_franklin.jpg
pidb/static/img/logo.png
pidb/static/img/logo.svg
pidb/static/img/logo_trans.svg
pidb/static/img/van_gogh_wheatfield_with_crows.jpg
pidb/static/js/forge.min.js
pidb/static/js/misc_jquery.js
pidb/templates/_macros.html
pidb/templates/base.html
pidb/templates/base_email.html
pidb/templates/experiment.html
pidb/templates/experiments.html
pidb/templates/finding.html
pidb/templates/findings.html
pidb/templates/generic_email.html
pidb/templates/index.html
pidb/templates/mail.html
pidb/templates/mail_sent.html
pidb/templates/user.html
pidb/templates/userroles.html
pidb/templates/users.html
pidb/templates/error/forbidden.html
pidb/templates/error/notfound.html
pidb/templates/security/change_password.html
pidb/templates/security/forgot_password.html
pidb/templates/security/login_user.html
pidb/templates/security/register_user.html
pidb/templates/security/reset_password.html
pidb/templates/security/send_confirmation.html
pidb/templates/security/two_factor_setup.html
pidb/templates/security/two_factor_verify_code.html
pidb/templates/security/email/change_notice.html
pidb/templates/security/email/change_notice.txt
pidb-6.1.2.dist-info/LICENSE
pidb-6.1.2.dist-info/METADATA
pidb-6.1.2.dist-info/WHEEL
pidb-6.1.2.dist-info/entry_points.txt
pidb-6.1.2.dist-info/top_level.txt
pidb-6.1.2.dist-info/RECORD
