Metadata-Version: 2.1
Name: pidb
Version: 6.1.2
Summary: Population Imaging Database (pidb) is a tool for collecting derived data in population imaging studies.
Home-page: https://gitlab.com/radiology/population-imaging/population-imaging-database
Author: H.C. Achterberg, M. Koek, A. Versteeg, T. Phil, M. Birhanu
Author-email: h.achterberg@erasmusmc.nl, m.koek@erasmusmc.nl, a.versteeg@erasmusmc.nl, t.phil@erasmusmc.nl, m.birhanu@erasmusmc.nl
License: LICENSE
Project-URL: Documentation, https://population-imaging-database.readthedocs.io
Project-URL: Code, https://gitlab.com/radiology/population-imaging/population-imaging-database
Project-URL: Issue tracker, https://gitlab.com/radiology/population-imaging/population-imaging-database/issues
Platform: UNKNOWN
Classifier: Development Status :: 4 - Beta
Classifier: Intended Audience :: Developers
Classifier: Intended Audience :: Science/Research
Classifier: Intended Audience :: Healthcare Industry
Classifier: Intended Audience :: Information Technology
Classifier: Intended Audience :: Education
Classifier: License :: OSI Approved :: Apache Software License
Classifier: Natural Language :: English
Classifier: Operating System :: OS Independent
Classifier: Programming Language :: Python :: 3.6
Classifier: Programming Language :: Python :: 3.7
Classifier: Programming Language :: Python :: 3 :: Only
Classifier: Topic :: Scientific/Engineering :: Information Analysis
Classifier: Topic :: System :: Logging
Classifier: Topic :: Utilities
Requires-Python: !=2.*,!=3.0.*,!=3.1.*,!=3.2.*,!=3.3.*,!=3.4.*,!=3.5.*
Requires-Dist: alembic (==1.3.2)
Requires-Dist: bcrypt (==3.1.7)
Requires-Dist: bleach (==3.3.0)
Requires-Dist: email-validator (==1.1.3)
Requires-Dist: Flask (==1.1.4)
Requires-Dist: Flask-BabelEx (==0.9.4)
Requires-Dist: Flask-Login (==0.5.0)
Requires-Dist: Flask-Mail (==0.9.1)
Requires-Dist: Flask-Migrate (==2.5.2)
Requires-Dist: flask-restx (==0.4.0)
Requires-Dist: Flask-Script (==2.0.6)
Requires-Dist: Flask-Security-Too (==4.0.1)
Requires-Dist: flask-shell-ipython (==0.4.1)
Requires-Dist: Flask-SQLAlchemy (==2.5.1)
Requires-Dist: Flask-WTF (==0.15.1)
Requires-Dist: marshmallow (==2.15.0)
Requires-Dist: PyMySQL (==0.9.3)
Requires-Dist: python-dotenv (==0.10.3)
Requires-Dist: PyYAML (==5.3.1)
Requires-Dist: requests (==2.22.0)
Requires-Dist: sqlalchemy (==1.3.12)
Requires-Dist: Sphinx (==2.1.2)
Requires-Dist: sphinx-rtd-theme (==0.4.3)
Requires-Dist: sphinx-autodoc-typehints (==1.7.0)
Requires-Dist: sphinxcontrib-redoc (==1.5.1)
Requires-Dist: werkzeug (==1.0.1)
